nutcracker/__init__.py
nutcracker/models.py
nutcracker/utils.py
nutcracker/data/__init__.py
nutcracker/data/instance.py
nutcracker/data/instance_collection.py
nutcracker/data/pile.py
nutcracker/data/task.py
nutcracker/data/data_config/pile/hf-open-llm-leaderboard.yaml
nutcracker/data/data_config/pile/htest.yaml
nutcracker/data/data_config/pile/math.yaml
nutcracker/data/data_config/pile/mmlu.yaml
nutcracker/data/data_config/task/aqua-rat.yaml
nutcracker/data/data_config/task/arc-challenge.yaml
nutcracker/data/data_config/task/arc-easy.yaml
nutcracker/data/data_config/task/commonsenseqa.yaml
nutcracker/data/data_config/task/gsm8k.yaml
nutcracker/data/data_config/task/hellaswag.yaml
nutcracker/data/data_config/task/hhh-alignment-harmless.yaml
nutcracker/data/data_config/task/hhh-alignment-helpful.yaml
nutcracker/data/data_config/task/hhh-alignment-honest.yaml
nutcracker/data/data_config/task/hhh-alignment-other.yaml
nutcracker/data/data_config/task/htest-end-ly.yaml
nutcracker/data/data_config/task/htest-end-punctuation.yaml
nutcracker/data/data_config/task/htest-hyphenated-word.yaml
nutcracker/data/data_config/task/htest-palindrome.yaml
nutcracker/data/data_config/task/htest-repeated-word.yaml
nutcracker/data/data_config/task/htest-rhyme.yaml
nutcracker/data/data_config/task/htest-spelled-math.yaml
nutcracker/data/data_config/task/htest-spelled-number.yaml
nutcracker/data/data_config/task/htest-start-vowel.yaml
nutcracker/data/data_config/task/htest-uppercase.yaml
nutcracker/data/data_config/task/math-algebra.yaml
nutcracker/data/data_config/task/math-counting-and-probability.yaml
nutcracker/data/data_config/task/math-geometry.yaml
nutcracker/data/data_config/task/math-intermediate-algebra.yaml
nutcracker/data/data_config/task/math-number-theory.yaml
nutcracker/data/data_config/task/math-prealgebra.yaml
nutcracker/data/data_config/task/math-precalculus.yaml
nutcracker/data/data_config/task/medqa-usmle.yaml
nutcracker/data/data_config/task/mfq-30.yaml
nutcracker_py-0.0.2a2.dist-info/LICENSE.txt
nutcracker_py-0.0.2a2.dist-info/METADATA
nutcracker_py-0.0.2a2.dist-info/WHEEL
nutcracker_py-0.0.2a2.dist-info/top_level.txt
nutcracker_py-0.0.2a2.dist-info/RECORD
