Metadata-Version: 2.1
Name: nutcracker-py
Version: 0.0.2a2
Summary: streamline LLM evaluation
Author: Bruce W. Lee
Author-email: bruce@walnutresearch.com
Keywords: Evaluation
License-File: LICENSE.txt
Requires-Dist: anthropic ==0.26.1
Requires-Dist: boto3 ==1.34.115
Requires-Dist: botocore ==1.29.76
Requires-Dist: cohere ==5.5.3
Requires-Dist: numpy ==1.24.3
Requires-Dist: openai ==1.30.4
Requires-Dist: pytest ==7.4.0
Requires-Dist: PyYAML ==6.0.1
Requires-Dist: Requests ==2.32.3
Requires-Dist: setuptools ==68.0.0
Requires-Dist: tqdm ==4.65.0
